cheetiming/__init__.py
cheetiming/_version.py
cheetiming/timer_manager.py
cheetiming/timing_session.py
cheetiming-0.0.4.dist-info/LICENSE
cheetiming-0.0.4.dist-info/METADATA
cheetiming-0.0.4.dist-info/WHEEL
cheetiming-0.0.4.dist-info/top_level.txt
cheetiming-0.0.4.dist-info/RECORD
