Metadata-Version: 2.1
Name: cheetiming
Version: 0.0.4
Summary: A package for timing with zero overhead
Author-email: OK111 <oleg.khadartsev@gmail.com>
Project-URL: Homepage, https://github.com/OlegKhadartsev/cheetiming
Classifier: Programming Language :: Python :: 3
Classifier: Operating System :: OS Independent
Requires-Python: >=3.7
License-File: LICENSE
